{
  "version": "32.0.0",
  "files": {
    "ae65d512cfd9743c23c28e22226289fa156fa17f87268bbd9ec1b7a324cd7d43": {
      "source": {
        "path": "cdk-ec2-infinity-admin.template.json",
        "packaging": "file"
      },
      "destinations": {
        "current_account-current_region": {
          "bucketName": "cdk-hnb659fds-assets-${AWS::AccountId}-${AWS::Region}",
          "objectKey": "ae65d512cfd9743c23c28e22226289fa156fa17f87268bbd9ec1b7a324cd7d43.json",
          "assumeRoleArn": "arn:${AWS::Partition}:iam::${AWS::AccountId}:role/cdk-hnb659fds-file-publishing-role-${AWS::AccountId}-${AWS::Region}"
        }
      }
    }
  },
  "dockerImages": {}
}